include/__init__.py
include/main.py
python_include/__init__.py
python_include/main.py
python_include-2.0.0.dist-info/METADATA
python_include-2.0.0.dist-info/WHEEL
python_include-2.0.0.dist-info/top_level.txt
python_include-2.0.0.dist-info/RECORD
