Metadata-Version: 2.1
Name: python-include
Version: 2.0.0
Summary: Relative imports that actually work
Home-page: https://github.com/jeff-hykin/python-include
Author: Jeff Hykin
Author-email: jeff.hykin@gmail.com
License: MIT
Platform: UNKNOWN
Requires-Python: >=3.6
